{
    "os": "Linux-5.10.16.3-microsoft-standard-WSL2-x86_64-with-glibc2.10",
    "python": "3.8.13",
    "heartbeatAt": "2022-05-05T23:38:15.470142",
    "startedAt": "2022-05-05T23:38:14.456667",
    "docker": null,
    "cpu_count": 8,
    "cuda": null,
    "args": [
        "artifact",
        "put",
        "--name",
        "exercise_4/genres_mod.parquet",
        "--type",
        "raw_data",
        "--description",
        "A modified version of the songs dataset",
        "genres_mod.parquet"
    ],
    "state": "running",
    "program": "/home/jledesmau/miniconda3/envs/udacity/bin/wandb",
    "git": {
        "remote": "https://github.com/jledesmau/build-model-workflow-exercises.git",
        "commit": "257cca3dc3ff32cedb0cc453dd77b6a78a8ff18f"
    },
    "email": "jledesmau@gmail.com",
    "root": "/home/jledesmau/build-model-workflow-exercises",
    "host": "LAPTOP-OPH8MA4M",
    "username": "jledesmau",
    "executable": "/home/jledesmau/miniconda3/envs/udacity/bin/python3.8"
}
